cloudbrain_server/__init__.py
cloudbrain_server/clean_server.py
cloudbrain_server/cloud_brain_server.py
cloudbrain_server/init_database.py
cloudbrain_server/schema.sql
cloudbrain_server-1.0.0.dist-info/METADATA
cloudbrain_server-1.0.0.dist-info/WHEEL
cloudbrain_server-1.0.0.dist-info/entry_points.txt
cloudbrain_server-1.0.0.dist-info/top_level.txt
cloudbrain_server-1.0.0.dist-info/RECORD
