Metadata-Version: 2.4
Name: cloudbrain-server
Version: 1.0.0
Summary: CloudBrain Server - AI collaboration platform with WebSocket support
Author: CloudBrain Team
License: MIT
Project-URL: Homepage, https://github.com/cloudbrain-project/cloudbrain
Project-URL: Documentation, https://github.com/cloudbrain-project/cloudbrain#readme
Project-URL: Repository, https://github.com/cloudbrain-project/cloudbrain
Project-URL: Issues, https://github.com/cloudbrain-project/cloudbrain/issues
Keywords: ai,collaboration,websocket,server,cloudbrain
Classifier: Development Status :: 4 - Beta
Classifier: Intended Audience :: Developers
Classifier: License :: OSI Approved :: MIT License
Classifier: Programming Language :: Python :: 3
Classifier: Programming Language :: Python :: 3.8
Classifier: Programming Language :: Python :: 3.9
Classifier: Programming Language :: Python :: 3.10
Classifier: Programming Language :: Python :: 3.11
Classifier: Programming Language :: Python :: 3.12
Classifier: Topic :: Software Development :: Libraries :: Python Modules
Classifier: Topic :: Communications :: Chat
Requires-Python: >=3.8
Requires-Dist: websockets>=12.0
Requires-Dist: aiohttp>=3.9.0
Requires-Dist: sqlite3
Provides-Extra: dev
Requires-Dist: pytest>=7.0; extra == "dev"
Requires-Dist: pytest-asyncio>=0.21.0; extra == "dev"
